{
  "name": "flair_with_custom_phone_pipeline",
  "description": "Pipeline using Flair model and custom German phone recognizer for German entity detection",
  "models": [],
  "recognizers": [
    {
      "name": "flair_recognizer",
      "config": {},
      "config_path": "user_configs/models/flair_recognizer.json"
    },
    {
      "name": "german_phone_recognizer",
      "config": {},
      "config_path": "user_configs/recognizers/german_phone_recognizer.json"
    }
  ],
  "operators": [
    {
      "name": "entity_sanitizer",
      "config_path": "user_configs/operators/entity_sanitizer.json"
    },
    {
      "name": "presidio_operator",
      "config": {
        "anonymization_method": "replace",
        "language": "de"
      },
      "config_path": null
    }
  ]
} 